solrstice-0.14.0.dist-info/METADATA
solrstice-0.14.0.dist-info/WHEEL
solrstice-0.14.0.dist-info/licenses/LICENSE-APACHE
solrstice-0.14.0.dist-info/licenses/LICENSE-MIT
solrstice.libs/libgcc_s-0366c7ba.so.1
solrstice/__init__.py
solrstice/_solrstice.abi3.so
solrstice/_solrstice.pyi
solrstice/alias.pyi
solrstice/collection.pyi
solrstice/config.pyi
solrstice/external.pyi
solrstice/models.pyi
solrstice/py.typed
solrstice-0.14.0.dist-info/RECORD
