Metadata-Version: 2.4
Name: solrstice
Version: 0.14.0
Classifier: Programming Language :: Rust
Classifier: Programming Language :: Python
Classifier: Programming Language :: Python :: 3
Classifier: Programming Language :: Python :: 3 :: Only
Classifier: Programming Language :: Python :: 3.9
Classifier: Programming Language :: Python :: 3.10
Classifier: Programming Language :: Python :: 3.11
Classifier: Programming Language :: Python :: 3.12
Classifier: Programming Language :: Python :: 3.13
Classifier: Programming Language :: Python :: Implementation :: CPython
Classifier: Development Status :: 4 - Beta
Classifier: Intended Audience :: Developers
Classifier: Topic :: Internet :: WWW/HTTP :: Indexing/Search
Classifier: License :: OSI Approved :: MIT License
Classifier: License :: OSI Approved :: Apache Software License
Classifier: Operating System :: POSIX :: Linux
Classifier: Operating System :: Microsoft :: Windows
Classifier: Operating System :: MacOS
Classifier: Typing :: Typed
License-File: LICENSE-APACHE
License-File: LICENSE-MIT
Summary: A Solr client library written in Rust
Keywords: solr,rust,search
License-Expression: MIT OR Apache-2.0
Requires-Python: >=3.9
Project-URL: Homepage, https://github.com/Sh1nku/solrstice
Project-URL: Repository, https://github.com/Sh1nku/solrstice
